Metadata-Version: 2.1
Name: d2p
Version: 1.0.0
Summary: exchange xml comments from you-get to plain text comments.
Home-page: https://github.com/sc-1123/d2p
Author: Jian Gao
Author-email: 2125587278@qq.com
Maintainer: Jian Gao
Maintainer-email: 2125587278@qq.com
License: UNKNOWN
Keywords: exchange
Platform: any
Classifier: Programming Language :: Python :: 3
Classifier: License :: OSI Approved :: MIT License
Classifier: Operating System :: OS Independent
